http_proxy_wrapper
