Metadata-Version: 1.0
Name: hpw
Version: 0.1.1
Summary: hpw is a command line utility for running and retrying any command using HTTP proxies
Home-page: UNKNOWN
Author: Rodrigo Argüello Flores
Author-email: rarguellof91@gmail.com
License: UNKNOWN
Platform: UNKNOWN
